plurals/__init__.py
plurals/agent.py
plurals/anes-mapping.yaml
plurals/deliberation.py
plurals/helpers.py
plurals/instructions.yaml
plurals/tests.py
plurals/data/__init.py__
plurals/data/anes_pilot_2022_20221214.csv
plurals/data/anes_pilot_2024_20240319.csv
plurals-0.3.dist-info/METADATA
plurals-0.3.dist-info/WHEEL
plurals-0.3.dist-info/top_level.txt
plurals-0.3.dist-info/RECORD
