Metadata-Version: 2.4
Name: plurals
Version: 0.3
Summary: A package for simulated social ensembles.
Home-page: https://github.com/josh-ashkinaze/plurals
Author: Joshua Ashkinaze
Author-email: josh.ashkinaze@gmail.com
Project-URL: Homepage, https://github.com/josh-ashkinaze/plurals
Project-URL: Documentation, https://josh-ashkinaze.github.io/plurals
Classifier: Programming Language :: Python :: 3
Classifier: License :: OSI Approved :: MIT License
Classifier: Operating System :: OS Independent
Requires-Python: >=3.6
Requires-Dist: pandas<3.0.0,>=2.2.0
Requires-Dist: PyYAML==6.0.1
Requires-Dist: litellm==1.40.0
Requires-Dist: build
Dynamic: author
Dynamic: author-email
Dynamic: classifier
Dynamic: description
Dynamic: description-content-type
Dynamic: home-page
Dynamic: project-url
Dynamic: requires-dist
Dynamic: requires-python
Dynamic: summary
